tests/__init__.py
tests/utils.py
tests/fileutils/__init__.py
tests/fileutils/basefs.py
tests/fileutils/basezip.py
tests/fileutils/test_diskfs.py
tests/fileutils/test_pathcache.py
tests/fileutils/test_zip.py
tests/fileutils/test_zipfs.py
tests/processors/__init__.py
tests/processors/base.py
tests/processors/test_mime.py
tests/render/__init__.py
tests/render/base.py
tests/render/test_jinjaloader.py
tests/render/test_jinjarender.py
tests/render/filters/__init__.py
tests/render/filters/base.py
tests/render/filters/test_jinjafilters.py
tests/report/__init__.py
tests/report/test_builder.py
tests/report/test_job.py
tests/report/test_loader.py
zipreport/__init__.py
zipreport/version.py
zipreport/zipreport.py
zipreport/cli/__init__.py
zipreport/cli/console.py
zipreport/cli/debug/__init__.py
zipreport/cli/debug/server.py
zipreport/fileutils/__init__.py
zipreport/fileutils/diskfs.py
zipreport/fileutils/interface.py
zipreport/fileutils/pathcache.py
zipreport/fileutils/zipfs.py
zipreport/fileutils/backend/__init__.py
zipreport/fileutils/backend/zip.py
zipreport/misc/__init__.py
zipreport/misc/html.py
zipreport/processors/__init__.py
zipreport/processors/interface.py
zipreport/processors/mime.py
zipreport/processors/weasyprint.py
zipreport/processors/wkhtmltopdf.py
zipreport/processors/zipreport.py
zipreport/report/__init__.py
zipreport/report/builder.py
zipreport/report/const.py
zipreport/report/job.py
zipreport/report/loader.py
zipreport/report/reportfile.py
zipreport/template/__init__.py
zipreport/template/jinjaloader.py
zipreport/template/jinjarender.py
zipreport/template/jinja/__init__.py
zipreport/template/jinja/filters.py
zipreport_lib-0.9.5.dist-info/LICENSE
zipreport_lib-0.9.5.dist-info/METADATA
zipreport_lib-0.9.5.dist-info/WHEEL
zipreport_lib-0.9.5.dist-info/entry_points.txt
zipreport_lib-0.9.5.dist-info/top_level.txt
zipreport_lib-0.9.5.dist-info/RECORD
