Metadata-Version: 2.1
Name: zipreport-lib
Version: 0.9.5
Summary: Python HTML to PDF reporting engine
Home-page: https://github.com/zipreport/zipreport
Author: Joao Pinheiro
Author-email: 
License: MIT
Project-URL: Documentation, https://zipreport.readthedocs.io/en/latest/
Project-URL: Source, https://github.com/zipreport/zipreport
Project-URL: Tracker, https://github.com/zipreport/zipreport/issues
Platform: UNKNOWN
Classifier: Development Status :: 4 - Beta
Classifier: Intended Audience :: Developers
Classifier: License :: OSI Approved :: MIT License
Classifier: Programming Language :: Python :: 3
Classifier: Programming Language :: Python :: 3.6
Classifier: Programming Language :: Python :: 3.7
Classifier: Programming Language :: Python :: 3.8
Classifier: Topic :: Internet :: WWW/HTTP
Classifier: Topic :: Text Processing :: Markup :: HTML
Classifier: Topic :: Printing
Requires-Python: >=3.6
License-File: LICENSE
Requires-Dist: jinja2 (<3.1)
Requires-Dist: requests (>=2.22.0)
Provides-Extra: weasyprint
Requires-Dist: weasyprint (>=3.5.0) ; extra == 'weasyprint'
